LICENSE
README.md
setup.py
paper_candy.egg-info/PKG-INFO
paper_candy.egg-info/SOURCES.txt
paper_candy.egg-info/dependency_links.txt
paper_candy.egg-info/requires.txt
paper_candy.egg-info/top_level.txt
papercandy/__init__.py
papercandy/config.py
papercandy/dataloader.py
papercandy/drawing.py
papercandy/network.py
papercandy/test.py
papercandy/train.py
papercandy/version.py
papercandy/core/__init__.py
papercandy/core/config.py
papercandy/core/dataloader.py
papercandy/core/drawing.py
papercandy/core/network.py
papercandy/core/optional_modules.py
papercandy/core/singleton.py
papercandy/core/test.py
papercandy/core/train.py
papercandy/core/utils.py