Metadata-Version: 2.1
Name: paper-candy
Version: 1.0.2b0
Summary: A loosely coupled lightweight framework for deep learning papers.
Home-page: https://github.com/ATATC/PaperCandy
Author: ATATC
Author-email: futerry@outlook.com
License: Apache License 2.0
Platform: UNKNOWN
License-File: LICENSE
